logspark/__init__.py
logspark-0.0.0.dist-info/METADATA
logspark-0.0.0.dist-info/WHEEL
logspark-0.0.0.dist-info/top_level.txt
logspark-0.0.0.dist-info/RECORD
