Metadata-Version: 2.4
Name: logspark
Version: 0.0.0
Summary: Logging control plane and unifier
Author: Willem van der Schans
License: MIT
Project-URL: Homepage, https://github.com/kydoimos97/logspark
Requires-Python: >=3.10
